README.md
setup.py
cyscore/__init__.py
cyscore/note.py
cyscore/score.py
cyscore/utility.py
cyscore/voice.py
cyscore.egg-info/PKG-INFO
cyscore.egg-info/SOURCES.txt
cyscore.egg-info/dependency_links.txt
cyscore.egg-info/top_level.txt