Metadata-Version: 1.2
Name: cyscore
Version: 0.2.7
Summary: score abstraction for csound written in python
Home-page: https://github.com/inkeye/cyscore
Author: Tim Pauli
Author-email: tim.pauli@folkwang-uni.de
License: GPL
Platform: UNKNOWN
Requires-Python: >=3.5
